upfp/__init__.py
upfp/core.py
upfp/iterator.py
upfp/tests/__init__.py
upfp/tests/test_core.py
upfp/tests/test_iterator.py
upfp/tests/utils.py
upfp-0.0.4.data/scripts/upfp-fasta-to-csv
upfp-0.0.4.dist-info/LICENSE
upfp-0.0.4.dist-info/METADATA
upfp-0.0.4.dist-info/WHEEL
upfp-0.0.4.dist-info/top_level.txt
upfp-0.0.4.dist-info/RECORD
