Metadata-Version: 2.1
Name: upfp
Version: 0.0.4
Summary: UPFP, a package to parse UniProt FASTA files.
Home-page: https://github.com/drugilsberg/uniprot_fasta_parser
Author: Matteo Manica
Author-email: drugilsberg@gmail.com
License: MIT
Platform: UNKNOWN
Classifier: Intended Audience :: Developers
Classifier: Intended Audience :: Science/Research
Classifier: License :: OSI Approved :: MIT License
Classifier: Programming Language :: Python :: 3
Classifier: Programming Language :: Python :: 3.6
Classifier: Programming Language :: Python :: 3.7
Classifier: Topic :: Software Development :: Libraries :: Python Modules
Requires-Dist: pandas (>=0.24.2)
